tell_me_your_secrets/__init__.py
tell_me_your_secrets/__main__.py
tell_me_your_secrets/config.yml
tell_me_your_secrets/defaults.py
tell_me_your_secrets/logger.py
tell_me_your_secrets/processor.py
tell_me_your_secrets/utils.py
tell_me_your_secrets-2.4.2.dist-info/LICENSE.txt
tell_me_your_secrets-2.4.2.dist-info/METADATA
tell_me_your_secrets-2.4.2.dist-info/WHEEL
tell_me_your_secrets-2.4.2.dist-info/entry_points.txt
tell_me_your_secrets-2.4.2.dist-info/RECORD
