Metadata-Version: 2.1
Name: tell-me-your-secrets
Version: 2.4.2
Summary: A simple module which finds files with different secrets keys present inside a directory
Home-page: https://github.com/valayDave/tell-me-your-secrets
License: MIT
Keywords: Security,SSH,Secret Keys,SysAdmin
Author: Valay Dave
Author-email: valaygaurang@gmail.com
Requires-Python: >=3.7.1,<4.0.0
Classifier: License :: OSI Approved :: MIT License
Classifier: Programming Language :: Python :: 3
Classifier: Programming Language :: Python :: 3.8
Classifier: Programming Language :: Python :: 3.9
Classifier: Programming Language :: Python :: 3.10
Classifier: Programming Language :: Python :: 3.11
Requires-Dist: PyYAML (>=6.0,<7.0)
Requires-Dist: gitignore-parser (>=0.1.3,<0.2.0)
Requires-Dist: pandas (>=1.3,<2.0)
Requires-Dist: single-source (>=0.3.0,<0.4.0)
Project-URL: Repository, https://github.com/valayDave/tell-me-your-secrets
